{
    "Ar36": {
        "error": 0.0002184877283665013,
        "error_type": "",
        "fit": "previous",
        "references": [
            {
                "exclude": false,
                "record_id": "ba-01-A-22499"
            }
        ],
        "value": 0.008669865072816422
    },
    "Ar37": {
        "error": 0.008890729284467892,
        "error_type": "",
        "fit": "previous",
        "references": [
            {
                "exclude": false,
                "record_id": "ba-01-A-22499"
            }
        ],
        "value": 0.060255991990482496
    },
    "Ar38": {
        "error": 0.010777883476234248,
        "error_type": "",
        "fit": "previous",
        "references": [
            {
                "exclude": false,
                "record_id": "ba-01-A-22499"
            }
        ],
        "value": 0.03502470057076916
    },
    "Ar39": {
        "error": 0.008664490418881468,
        "error_type": "",
        "fit": "previous",
        "references": [
            {
                "exclude": false,
                "record_id": "ba-01-A-22499"
            }
        ],
        "value": 0.10663170037530577
    },
    "Ar40": {
        "error": 0.022207461651262538,
        "error_type": "",
        "fit": "previous",
        "references": [
            {
                "exclude": false,
                "record_id": "ba-01-A-22499"
            }
        ],
        "value": 0.7334555688275769
    }
}